monday_api_python_sdk-1.6.0.dist-info/licenses/LICENSE
monday_sdk/__init__.py
monday_sdk/client.py
monday_sdk/constants.py
monday_sdk/exceptions.py
monday_sdk/graphql_handler.py
monday_sdk/query_templates.py
monday_sdk/utils.py
monday_sdk/modules/__init__.py
monday_sdk/modules/activity_logs.py
monday_sdk/modules/boards.py
monday_sdk/modules/custom.py
monday_sdk/modules/docs.py
monday_sdk/modules/items.py
monday_sdk/modules/updates.py
monday_sdk/types/__init__.py
monday_sdk/types/api_response_types.py
monday_sdk/types/file_input.py
monday_sdk/types/monday_enums.py
monday_api_python_sdk-1.6.0.dist-info/METADATA
monday_api_python_sdk-1.6.0.dist-info/WHEEL
monday_api_python_sdk-1.6.0.dist-info/top_level.txt
monday_api_python_sdk-1.6.0.dist-info/RECORD
