Metadata-Version: 2.4
Name: monday-api-python-sdk
Version: 1.6.0
Summary: A Python SDK for interacting with Monday's GraphQL API.
Home-page: https://github.com/mondaycom/monday-api-python-sdk
Author: Michael Imas
Author-email: Michael Imas <michaelim@monday.com>
Maintainer-email: Rafał Zawadzki <rafalza@monday.com>
Requires-Python: >=3.7, <4
License-File: LICENSE
Requires-Dist: dacite
Requires-Dist: requests
Dynamic: author
Dynamic: home-page
Dynamic: license-file
Dynamic: requires-python
